[
  {
    "content_id": 238036,
    "reference_id": 25903,
    "title": "Líderes judeus",
    "media_type": "Text",
    "index_reference": "líderes judeus",
    "language": "por",
    "content": "<h1>autoridades judaicas, líder judeu</h1><h2>Fatos:</h2><p>O termo “líder judeu” ou “autoridade judaica” refere-se a líderes religiosos como os sacerdotes e mestres das leis de Deus. Eles também tinham autoridade para fazer julgamentos sobre assuntos não religiosos.</p><ul><li><p>Os líderes judeus eram os sumos sacerdotes, principais sacerdotes e escribas (mestres das leis de Deus).</p></li><li><p>Dois principais grupos de líderes judeus eram os fariseus e saduceus.</p></li><li><p>Setenta líderes judeus se reuniam no Conselho Judaico em Jerusalém para fazer julgamentos sobre questões da lei.</p></li><li><p>Muitos líderes judeus eram orgulhosos e achavam que eram justos. Eles tinham inveja de Jesus e queriam prejudicá-lo. Eles alegavam conhecer Deus, mas não o obedeciam.</p></li><li><p>Muitas vezes a frase “os judeus” referia-se aos líderes judeus, especialmente em contextos onde estavam zangados com Jesus e tentavam enganá-lo ou prejudicá-lo.</p></li><li><p>Esses termos também poderiam ser traduzidos como “governantes judeus” ou “homens que governavam sobre o povo judeu” ou “líderes religiosos judeus”.</p></li></ul><p>(Veja também: <span data-bnType=\"resourceReference\" data-resourceId=\"25902\" data-resourceType=\"UWTranslationWords\">Judeu</span>, <span data-bnType=\"resourceReference\" data-resourceId=\"25616\" data-resourceType=\"UWTranslationWords\">conselho</span>, <span data-bnType=\"resourceReference\" data-resourceId=\"25836\" data-resourceType=\"UWTranslationWords\">sumo sacerdote</span>, <span data-bnType=\"resourceReference\" data-resourceId=\"26095\" data-resourceType=\"UWTranslationWords\">fariseu</span>, <span data-bnType=\"resourceReference\" data-resourceId=\"26121\" data-resourceType=\"UWTranslationWords\">sacerdote</span>, <span data-bnType=\"resourceReference\" data-resourceId=\"26189\" data-resourceType=\"UWTranslationWords\">saduceu</span>, <span data-bnType=\"resourceReference\" data-resourceId=\"26204\" data-resourceType=\"UWTranslationWords\">escriba</span>)</p><h2>Referências Bíblicas:</h2><ul><li><p><a href=\"https://ref.ly/Exod16:22-Exod16:23\">Êxodo 16.22–23</a></p></li><li><p><a href=\"https://ref.ly/John2:19\">João 2.19</a></p></li><li><p><a href=\"https://ref.ly/John5:10-John5:11\">João 5.10–11</a></p></li><li><p><a href=\"https://ref.ly/John5:16\">João 5.16</a></p></li><li><p><a href=\"https://ref.ly/Luke19:47-Luke19:48\">Lucas 19.47–48</a></p></li></ul><h2>Exemplos das histórias bíblicas:</h2><ul><li><p><strong>24:3</strong> Muitos <strong>líderes religiosos</strong> também vieram para ser batizados por João, mas eles não se arrependeram nem confessaram seus pecados.</p></li><li><p><strong>37:11</strong> Mas os <strong>líderes religiosos dos judeus</strong> estavam com inveja, então se reuniram para planejar como poderiam matar Jesus e Lázaro.</p></li><li><p><strong>38:2</strong> Ele (Judas) sabia que os <strong>líderes judeus</strong> negavam que Jesus era o Messias e que estavam conspirando para matá-lo.</p></li><li><p><strong>38:3</strong> Os <strong>líderes judeus</strong>, liderados pelo sumo sacerdote, pagaram a Judas trinta moedas de prata para trair Jesus.</p></li><li><p><strong>39:5</strong> Todos os <strong>líderes judeus</strong> responderam ao sumo sacerdote, “Ele (Jesus) merece morrer!”.</p></li><li><p><strong>39:9</strong> Na manhã seguinte, os <strong>líderes judeus</strong> levaram Jesus a Pilatos, o governador romano.</p></li><li><p><strong>39:11</strong> Mas os <strong>líderes judeus</strong> e a multidão gritaram, “Crucifica-o!”.</p></li><li><p><strong>40:9</strong> Então José e Nicodemos, dois <strong>líderes judeus</strong> que acreditavam que Jesus era o Messias, pediram a Pilatos o corpo de Jesus.</p></li><li><p><strong>44:7</strong> No dia seguinte, os <strong>líderes judeus</strong> trouxeram Pedro e João ao sumo sacerdote e aos outros <strong>líderes religiosos</strong>.</p></li></ul><h2>Dados da Palavra:</h2><ul><li><p>Strong’s: G24530</p></li></ul>",
    "associations": {
      "passage": [
        {
          "start_ref": "43002019",
          "start_ref_usfm": "JHN 2:19",
          "end_ref": "43002019",
          "end_ref_usfm": "JHN 2:19"
        },
        {
          "start_ref": "43005016",
          "start_ref_usfm": "JHN 5:16",
          "end_ref": "43005016",
          "end_ref_usfm": "JHN 5:16"
        },
        {
          "start_ref": "02016022",
          "start_ref_usfm": "EXO 16:22",
          "end_ref": "02016023",
          "end_ref_usfm": "EXO 16:23"
        },
        {
          "start_ref": "43005010",
          "start_ref_usfm": "JHN 5:10",
          "end_ref": "43005011",
          "end_ref_usfm": "JHN 5:11"
        },
        {
          "start_ref": "42019047",
          "start_ref_usfm": "LUK 19:47",
          "end_ref": "42019048",
          "end_ref_usfm": "LUK 19:48"
        }
      ],
      "resource": [
        {
          "reference_id": 25616,
          "content_id": 237750,
          "resource_code": "UWTranslationWords",
          "label": "Conselho",
          "language": "por"
        },
        {
          "reference_id": 25836,
          "content_id": 237969,
          "resource_code": "UWTranslationWords",
          "label": "Sumo Sacerdote",
          "language": "por"
        },
        {
          "reference_id": 25902,
          "content_id": 238035,
          "resource_code": "UWTranslationWords",
          "label": "Judeu",
          "language": "por"
        },
        {
          "reference_id": 26095,
          "content_id": 238225,
          "resource_code": "UWTranslationWords",
          "label": "Fariseu",
          "language": "por"
        },
        {
          "reference_id": 26121,
          "content_id": 238251,
          "resource_code": "UWTranslationWords",
          "label": "Sacerdote",
          "language": "por"
        },
        {
          "reference_id": 26189,
          "content_id": 238318,
          "resource_code": "UWTranslationWords",
          "label": "Saduceu",
          "language": "por"
        },
        {
          "reference_id": 26204,
          "content_id": 238333,
          "resource_code": "UWTranslationWords",
          "label": "Escriba",
          "language": "por"
        }
      ]
    }
  }
]