[
  {
    "content_id": 467360,
    "reference_id": 26245,
    "title": "Abattage",
    "media_type": "Text",
    "index_reference": "abattage",
    "language": "fra",
    "content": "<h1>abattage</h1><h2>Définition :</h2><p>Le terme «abattage» est souvent utilisé pour exprimer le fait de tuer un grand nombre d&apos;animaux ou de personnes, ou de tuer d&apos;une manière violente* Il peut également signifier tuer quelques animaux pour les manger.</p><ul><li><p>Quand Abraham a reçu trois visiteurs dans sa tente dans le désert, il ordonna à ses serviteurs d&apos;abattre et cuire un veau gras pour ses invités.</p></li><li><p>Le prophète Ezéchiel a prophétisé que Dieu a envoyé son ange pour massacrer tous ceux qui ne suivent pas Sa Parole.</p></li><li><p>1 Samuel mentionne un grand carnage où 30 000 Israélites ont été tués par leurs ennemis à cause de la désobéissance à Dieu.</p></li><li><p>Ce terme peut aussi être traduit par &quot;meurtre&quot; ou &quot;tuerie&quot;.</p></li></ul><p>(Voir aussi : (../kt/angel.md), (../other/cow.md), (../other/disobey.md), (../names/ezekiel.md), (../other/servant.md), (../other/slain.md))</p>",
    "associations": {
      "passage": [
        {
          "start_ref": "01022010",
          "start_ref_usfm": "GEN 22:10",
          "end_ref": "01022010",
          "end_ref_usfm": "GEN 22:10"
        },
        {
          "start_ref": "01037031",
          "start_ref_usfm": "GEN 37:31",
          "end_ref": "01037031",
          "end_ref_usfm": "GEN 37:31"
        },
        {
          "start_ref": "01043016",
          "start_ref_usfm": "GEN 43:16",
          "end_ref": "01043016",
          "end_ref_usfm": "GEN 43:16"
        },
        {
          "start_ref": "02012006",
          "start_ref_usfm": "EXO 12:6",
          "end_ref": "02012006",
          "end_ref_usfm": "EXO 12:6"
        },
        {
          "start_ref": "02012021",
          "start_ref_usfm": "EXO 12:21",
          "end_ref": "02012021",
          "end_ref_usfm": "EXO 12:21"
        },
        {
          "start_ref": "02022001",
          "start_ref_usfm": "EXO 22:1",
          "end_ref": "02022001",
          "end_ref_usfm": "EXO 22:1"
        },
        {
          "start_ref": "02029011",
          "start_ref_usfm": "EXO 29:11",
          "end_ref": "02029011",
          "end_ref_usfm": "EXO 29:11"
        },
        {
          "start_ref": "02029016",
          "start_ref_usfm": "EXO 29:16",
          "end_ref": "02029016",
          "end_ref_usfm": "EXO 29:16"
        },
        {
          "start_ref": "02029020",
          "start_ref_usfm": "EXO 29:20",
          "end_ref": "02029020",
          "end_ref_usfm": "EXO 29:20"
        },
        {
          "start_ref": "15006020",
          "start_ref_usfm": "EZR 6:20",
          "end_ref": "15006020",
          "end_ref_usfm": "EZR 6:20"
        },
        {
          "start_ref": "20009002",
          "start_ref_usfm": "PRO 9:2",
          "end_ref": "20009002",
          "end_ref_usfm": "PRO 9:2"
        },
        {
          "start_ref": "20024011",
          "start_ref_usfm": "PRO 24:11",
          "end_ref": "20024011",
          "end_ref_usfm": "PRO 24:11"
        },
        {
          "start_ref": "23034002",
          "start_ref_usfm": "ISA 34:2",
          "end_ref": "23034002",
          "end_ref_usfm": "ISA 34:2"
        },
        {
          "start_ref": "24025034",
          "start_ref_usfm": "JER 25:34",
          "end_ref": "24025034",
          "end_ref_usfm": "JER 25:34"
        },
        {
          "start_ref": "31001009",
          "start_ref_usfm": "OBA 1:9",
          "end_ref": "31001009",
          "end_ref_usfm": "OBA 1:9"
        },
        {
          "start_ref": "44008032",
          "start_ref_usfm": "ACT 8:32",
          "end_ref": "44008032",
          "end_ref_usfm": "ACT 8:32"
        },
        {
          "start_ref": "45008036",
          "start_ref_usfm": "ROM 8:36",
          "end_ref": "45008036",
          "end_ref_usfm": "ROM 8:36"
        },
        {
          "start_ref": "58007001",
          "start_ref_usfm": "HEB 7:1",
          "end_ref": "58007001",
          "end_ref_usfm": "HEB 7:1"
        },
        {
          "start_ref": "59005005",
          "start_ref_usfm": "JAS 5:5",
          "end_ref": "59005005",
          "end_ref_usfm": "JAS 5:5"
        },
        {
          "start_ref": "66006004",
          "start_ref_usfm": "REV 6:4",
          "end_ref": "66006004",
          "end_ref_usfm": "REV 6:4"
        },
        {
          "start_ref": "26021010",
          "start_ref_usfm": "EZK 21:10",
          "end_ref": "26021011",
          "end_ref_usfm": "EZK 21:11"
        }
      ],
      "resource": [
        {
          "reference_id": 25459,
          "content_id": 466639,
          "resource_code": "Unknown",
          "label": "Ange",
          "language": "fra"
        },
        {
          "reference_id": 25623,
          "content_id": 466788,
          "resource_code": "Unknown",
          "label": "Vache ",
          "language": "fra"
        },
        {
          "reference_id": 26217,
          "content_id": 467334,
          "resource_code": "Unknown",
          "label": "Serviteur",
          "language": "fra"
        },
        {
          "reference_id": 25723,
          "content_id": 559325,
          "resource_code": "Unknown",
          "label": "Ézéchiel",
          "language": "fra"
        }
      ]
    }
  }
]