[
  {
    "content_id": 467237,
    "reference_id": 26114,
    "title": "Posséder",
    "media_type": "Text",
    "index_reference": "posséder",
    "language": "fra",
    "content": "<h1>posséder, possession</h1><h2>Définition :</h2><p>Les termes «possèder» et «possession» se réfèrent généralement à posséder quelque chose* Ils peuvent aussi signifier de prendre le contrôle ou d&apos;occuper une superficie de terres* Voici comment ils sont souvent utilisés dans la Bible.</p><ul><li><p>Dans l&apos;Ancien Testament, ce terme est souvent utilisé dans le contexte de «posséder» ou «prise de possession» d&apos;une superficie de terre.</p></li><li><p>Lorsque Yahvé ordonna aux Israélites de «posséder» la terre de Canaan, cela signifiait qu&apos;ils devraient aller dans le pays et y vivre* Cela a souvent impliqué d&apos;abord conquérir les peuples cananéens qui vivaient sur cette terre.</p></li><li><p>Yahvé dit aux Israélites qu&apos;il leur avait donné la terre de Canaan comme leur «possession», ce qui signifiait qu&apos;il allait les aider à vaincre les Cananéens et occuper le terrain.</p></li><li><p>Le peuple d&apos;Israël a également été appelé «possession spéciale de Yahweh*&quot; Cela signifie qu&apos;ils appartenaient à lui comme son peuple, qu&apos;il avait expressément appelé à l&apos;adorer et être gouverné par lui.</p></li></ul><h2>traduction Suggestions</h2><ul><li><p>Les termes «possèder» ou «prendre possession» pourrait être traduit par «prendre le contrôle de» ou «occuper» ou «vivre», selon le contexte.</p></li><li><p>Certaines langues peuvent traduire avec un terme qui est différent du mot de posséder ou de posséder un objet.</p></li><li><p>L&apos;expression «ma possession spéciale» pourrait être traduit par «mon peuple spécial» ou «les gens qui appartiennent à moi» ou «mon peuple que j&apos;aime et donne des conduites à tenir*&quot;</p></li><li><p>La phrase, &quot;ils deviendront leur possession&quot; en se référant à la terre, signifie «ils vont occuper le terrain» ou «la terre appartient à eux*&quot;</p></li><li><p>L&apos;expression «trouvé en sa possession&quot; pourrait être traduite comme &quot;qu&apos;il tenait&quot; ou &quot;qu&apos;il avait avec lui*&quot;</p></li><li><p>Le terme «biens» fait référence à des choses qui appartiennent à quelqu&apos;un et pourrait être traduit comme «biens» ou «propriété» ou «les choses appartenant à*&quot;</p></li><li><p>L&apos;expression «en votre possession&quot; pourrait être traduit par une phrase qui signifie «comme quelque chose qui vous appartient*&quot;</p></li></ul><p>(Voir aussi : (../names/canaan.md), (../kt/worship.md))</p>",
    "associations": {
      "passage": [
        {
          "start_ref": "01015007",
          "start_ref_usfm": "GEN 15:7",
          "end_ref": "01015007",
          "end_ref_usfm": "GEN 15:7"
        },
        {
          "start_ref": "01015008",
          "start_ref_usfm": "GEN 15:8",
          "end_ref": "01015008",
          "end_ref_usfm": "GEN 15:8"
        },
        {
          "start_ref": "01017008",
          "start_ref_usfm": "GEN 17:8",
          "end_ref": "01017008",
          "end_ref_usfm": "GEN 17:8"
        },
        {
          "start_ref": "01022017",
          "start_ref_usfm": "GEN 22:17",
          "end_ref": "01022017",
          "end_ref_usfm": "GEN 22:17"
        },
        {
          "start_ref": "01024060",
          "start_ref_usfm": "GEN 24:60",
          "end_ref": "01024060",
          "end_ref_usfm": "GEN 24:60"
        },
        {
          "start_ref": "01028004",
          "start_ref_usfm": "GEN 28:4",
          "end_ref": "01028004",
          "end_ref_usfm": "GEN 28:4"
        },
        {
          "start_ref": "01034010",
          "start_ref_usfm": "GEN 34:10",
          "end_ref": "01034010",
          "end_ref_usfm": "GEN 34:10"
        },
        {
          "start_ref": "01036043",
          "start_ref_usfm": "GEN 36:43",
          "end_ref": "01036043",
          "end_ref_usfm": "GEN 36:43"
        },
        {
          "start_ref": "01047011",
          "start_ref_usfm": "GEN 47:11",
          "end_ref": "01047011",
          "end_ref_usfm": "GEN 47:11"
        },
        {
          "start_ref": "01047027",
          "start_ref_usfm": "GEN 47:27",
          "end_ref": "01047027",
          "end_ref_usfm": "GEN 47:27"
        },
        {
          "start_ref": "01048004",
          "start_ref_usfm": "GEN 48:4",
          "end_ref": "01048004",
          "end_ref_usfm": "GEN 48:4"
        },
        {
          "start_ref": "02006008",
          "start_ref_usfm": "EXO 6:8",
          "end_ref": "02006008",
          "end_ref_usfm": "EXO 6:8"
        },
        {
          "start_ref": "02015009",
          "start_ref_usfm": "EXO 15:9",
          "end_ref": "02015009",
          "end_ref_usfm": "EXO 15:9"
        },
        {
          "start_ref": "02015017",
          "start_ref_usfm": "EXO 15:17",
          "end_ref": "02015017",
          "end_ref_usfm": "EXO 15:17"
        },
        {
          "start_ref": "02019005",
          "start_ref_usfm": "EXO 19:5",
          "end_ref": "02019005",
          "end_ref_usfm": "EXO 19:5"
        },
        {
          "start_ref": "02023030",
          "start_ref_usfm": "EXO 23:30",
          "end_ref": "02023030",
          "end_ref_usfm": "EXO 23:30"
        },
        {
          "start_ref": "13006070",
          "start_ref_usfm": "1CH 6:70",
          "end_ref": "13006070",
          "end_ref_usfm": "1CH 6:70"
        },
        {
          "start_ref": "20008022",
          "start_ref_usfm": "PRO 8:22",
          "end_ref": "20008022",
          "end_ref_usfm": "PRO 8:22"
        },
        {
          "start_ref": "20030009",
          "start_ref_usfm": "PRO 30:9",
          "end_ref": "20030009",
          "end_ref_usfm": "PRO 30:9"
        },
        {
          "start_ref": "20030023",
          "start_ref_usfm": "PRO 30:23",
          "end_ref": "20030023",
          "end_ref_usfm": "PRO 30:23"
        },
        {
          "start_ref": "40006002",
          "start_ref_usfm": "MAT 6:2",
          "end_ref": "40006002",
          "end_ref_usfm": "MAT 6:2"
        },
        {
          "start_ref": "40006005",
          "start_ref_usfm": "MAT 6:5",
          "end_ref": "40006005",
          "end_ref_usfm": "MAT 6:5"
        },
        {
          "start_ref": "40006016",
          "start_ref_usfm": "MAT 6:16",
          "end_ref": "40006016",
          "end_ref_usfm": "MAT 6:16"
        },
        {
          "start_ref": "40013044",
          "start_ref_usfm": "MAT 13:44",
          "end_ref": "40013044",
          "end_ref_usfm": "MAT 13:44"
        },
        {
          "start_ref": "40019021",
          "start_ref_usfm": "MAT 19:21",
          "end_ref": "40019021",
          "end_ref_usfm": "MAT 19:21"
        },
        {
          "start_ref": "40019022",
          "start_ref_usfm": "MAT 19:22",
          "end_ref": "40019022",
          "end_ref_usfm": "MAT 19:22"
        },
        {
          "start_ref": "40021038",
          "start_ref_usfm": "MAT 21:38",
          "end_ref": "40021038",
          "end_ref_usfm": "MAT 21:38"
        },
        {
          "start_ref": "40024047",
          "start_ref_usfm": "MAT 24:47",
          "end_ref": "40024047",
          "end_ref_usfm": "MAT 24:47"
        },
        {
          "start_ref": "40025014",
          "start_ref_usfm": "MAT 25:14",
          "end_ref": "40025014",
          "end_ref_usfm": "MAT 25:14"
        },
        {
          "start_ref": "41003027",
          "start_ref_usfm": "MRK 3:27",
          "end_ref": "41003027",
          "end_ref_usfm": "MRK 3:27"
        },
        {
          "start_ref": "41010022",
          "start_ref_usfm": "MRK 10:22",
          "end_ref": "41010022",
          "end_ref_usfm": "MRK 10:22"
        },
        {
          "start_ref": "42006024",
          "start_ref_usfm": "LUK 6:24",
          "end_ref": "42006024",
          "end_ref_usfm": "LUK 6:24"
        },
        {
          "start_ref": "42008003",
          "start_ref_usfm": "LUK 8:3",
          "end_ref": "42008003",
          "end_ref_usfm": "LUK 8:3"
        },
        {
          "start_ref": "42011021",
          "start_ref_usfm": "LUK 11:21",
          "end_ref": "42011021",
          "end_ref_usfm": "LUK 11:21"
        },
        {
          "start_ref": "42012015",
          "start_ref_usfm": "LUK 12:15",
          "end_ref": "42012015",
          "end_ref_usfm": "LUK 12:15"
        },
        {
          "start_ref": "42012033",
          "start_ref_usfm": "LUK 12:33",
          "end_ref": "42012033",
          "end_ref_usfm": "LUK 12:33"
        },
        {
          "start_ref": "42012044",
          "start_ref_usfm": "LUK 12:44",
          "end_ref": "42012044",
          "end_ref_usfm": "LUK 12:44"
        },
        {
          "start_ref": "42014033",
          "start_ref_usfm": "LUK 14:33",
          "end_ref": "42014033",
          "end_ref_usfm": "LUK 14:33"
        },
        {
          "start_ref": "42016001",
          "start_ref_usfm": "LUK 16:1",
          "end_ref": "42016001",
          "end_ref_usfm": "LUK 16:1"
        },
        {
          "start_ref": "42019008",
          "start_ref_usfm": "LUK 19:8",
          "end_ref": "42019008",
          "end_ref_usfm": "LUK 19:8"
        },
        {
          "start_ref": "44002045",
          "start_ref_usfm": "ACT 2:45",
          "end_ref": "44002045",
          "end_ref_usfm": "ACT 2:45"
        },
        {
          "start_ref": "44003006",
          "start_ref_usfm": "ACT 3:6",
          "end_ref": "44003006",
          "end_ref_usfm": "ACT 3:6"
        },
        {
          "start_ref": "44004032",
          "start_ref_usfm": "ACT 4:32",
          "end_ref": "44004032",
          "end_ref_usfm": "ACT 4:32"
        },
        {
          "start_ref": "44004037",
          "start_ref_usfm": "ACT 4:37",
          "end_ref": "44004037",
          "end_ref_usfm": "ACT 4:37"
        },
        {
          "start_ref": "44007005",
          "start_ref_usfm": "ACT 7:5",
          "end_ref": "44007005",
          "end_ref_usfm": "ACT 7:5"
        },
        {
          "start_ref": "44007045",
          "start_ref_usfm": "ACT 7:45",
          "end_ref": "44007045",
          "end_ref_usfm": "ACT 7:45"
        },
        {
          "start_ref": "46007030",
          "start_ref_usfm": "1CO 7:30",
          "end_ref": "46007030",
          "end_ref_usfm": "1CO 7:30"
        },
        {
          "start_ref": "46013003",
          "start_ref_usfm": "1CO 13:3",
          "end_ref": "46013003",
          "end_ref_usfm": "1CO 13:3"
        },
        {
          "start_ref": "47006010",
          "start_ref_usfm": "2CO 6:10",
          "end_ref": "47006010",
          "end_ref_usfm": "2CO 6:10"
        },
        {
          "start_ref": "49001014",
          "start_ref_usfm": "EPH 1:14",
          "end_ref": "49001014",
          "end_ref_usfm": "EPH 1:14"
        },
        {
          "start_ref": "52004004",
          "start_ref_usfm": "1TH 4:4",
          "end_ref": "52004004",
          "end_ref_usfm": "1TH 4:4"
        },
        {
          "start_ref": "58010034",
          "start_ref_usfm": "HEB 10:34",
          "end_ref": "58010034",
          "end_ref_usfm": "HEB 10:34"
        },
        {
          "start_ref": "60002009",
          "start_ref_usfm": "1PE 2:9",
          "end_ref": "60002009",
          "end_ref_usfm": "1PE 2:9"
        },
        {
          "start_ref": "11009017",
          "start_ref_usfm": "1KI 9:17",
          "end_ref": "11009019",
          "end_ref_usfm": "1KI 9:19"
        },
        {
          "start_ref": "05004005",
          "start_ref_usfm": "DEU 4:5",
          "end_ref": "05004006",
          "end_ref_usfm": "DEU 4:6"
        },
        {
          "start_ref": "01031036",
          "start_ref_usfm": "GEN 31:36",
          "end_ref": "01031037",
          "end_ref_usfm": "GEN 31:37"
        }
      ],
      "resource": [
        {
          "reference_id": 25572,
          "content_id": 466740,
          "resource_code": "Unknown",
          "label": "Canaan",
          "language": "fra"
        },
        {
          "reference_id": 25867,
          "content_id": 467013,
          "resource_code": "Unknown",
          "label": "Hériter",
          "language": "fra"
        },
        {
          "reference_id": 26357,
          "content_id": 467465,
          "resource_code": "Unknown",
          "label": "Adorer",
          "language": "fra"
        }
      ]
    }
  }
]