[
  {
    "content_id": 179741,
    "reference_id": 25665,
    "title": "घृणा",
    "media_type": "Text",
    "index_reference": "घृणा",
    "language": "hin",
    "content": "<h1>घृणा, घृणा करा, घृणित</h1><h2>तथ्य:</h2><p>“घृणित” शब्द कुछ ऐसी वस्तुओं का वर्णन करता है जिन्हें नापसंद और अस्वीकार करना चाहिए। किसी वस्तु से घृणा करने का अर्थ है उसे दृढ़ता से नापसंद करना।</p><ul><li><p>बाइबल प्रायः बुराई से घृणा की चर्चा करती है। इसका अर्थ है बुराई से घृणा करना और उसका त्याग करना।</p></li><li><p>परमेश्वर ने &quot;घृणित&quot; शब्द का प्रयोग उन लोगों के बुरे कामों का वर्णन करने के लिए किया, जो झूठे देवताओं की पूजा करते थे।</p></li><li><p>इस्राएलियों को आज्ञा दी गई थी कि वे पड़ोसी जातियों के पापी अनैतिक अभ्यासों से &quot;घृणा&quot; करें।</p></li><li><p>परमेश्वर ने सब अनुचित यौनाचार को &quot;घृणित&quot; कहा है।</p></li><li><p>भविष्य कहना, भूत सिद्धि करना तथा शिशु-बलि, सब परमेश्वर के लिए &quot;घृणित&quot; थे।</p></li><li><p>&quot;घृणा&quot; शब्द का अनुवाद &quot;दृढ़ता से अस्वीकार&quot; या &quot;नफरत&quot; या &quot;बहुत बुरा मानते हैं&quot; के रूप में किया जा सकता है ।</p></li><li><p>“घृणित” शब्द का अनुवाद “भयानक बुराई” या “घृणा योग्य” या “परित्याग के योग्य” किया जा सकता है।</p></li><li><p>जब दुष्ट को धर्मी &quot;घृणित&quot; करने के लिए आवेदन किया जाता है, तो इसे &quot;बहुत अवांछनीय माना जाता है&quot; या &quot;अयोग्य&quot; या &quot;अस्वीकार कर दिया&quot; के रूप में अनुवाद किया जा सकता है।</p></li><li><p>परमेश्वर ने कुछ प्रकार के जानवरों को &quot;घृणा&quot; करने के लिए इस्राएलियों से कहा था कि परमेश्वर ने उन्हें &quot;अशुद्ध&quot; और भोजन के लिए उपयुक्त नहीं घोषित किया था। * इसका अनुवाद “प्रबल नापसंदगी” या “परित्याग” या “अस्वीकार्य मानना” के रूप में किया जा सकता है।</p></li></ul><p>(यह भी देखें: <span data-bnType=\"resourceReference\" data-resourceId=\"25674\" data-resourceType=\"UWTranslationWords\">भविष्य कहना</span>, <span data-bnType=\"resourceReference\" data-resourceId=\"25596\" data-resourceType=\"UWTranslationWords\">शुद्ध</span>)</p><h2>बाइबल सन्दर्भ:</h2><ul><li><p><a href=\"https://ref.ly/Gen43:32\">उत्पत्ति 43:32</a></p></li><li><p><a href=\"https://ref.ly/Jer7:30\">यिर्मयाह 07:30</a></p></li><li><p><a href=\"https://ref.ly/Lev11:10\">लैव्यव्यवस्था 11:10</a></p></li><li><p><a href=\"https://ref.ly/Luke16:15\">लूका 16:15</a></p></li><li><p><a href=\"https://ref.ly/Rev17:3-Rev17:5\">प्रकाशितवाक्य 17:3–5</a></p></li></ul><h2>शब्द तथ्य:</h2><ul><li><p>स्ट्रांग&apos;स: H1602, H6973, H8130, H8251, H8262, H8263, H8441, H8581, G946, G947, G948, G4767, G3404</p></li></ul>",
    "associations": {
      "passage": [
        {
          "start_ref": "01043032",
          "start_ref_usfm": "GEN 43:32",
          "end_ref": "01043032",
          "end_ref_usfm": "GEN 43:32"
        },
        {
          "start_ref": "03011010",
          "start_ref_usfm": "LEV 11:10",
          "end_ref": "03011010",
          "end_ref_usfm": "LEV 11:10"
        },
        {
          "start_ref": "24007030",
          "start_ref_usfm": "JER 7:30",
          "end_ref": "24007030",
          "end_ref_usfm": "JER 7:30"
        },
        {
          "start_ref": "42016015",
          "start_ref_usfm": "LUK 16:15",
          "end_ref": "42016015",
          "end_ref_usfm": "LUK 16:15"
        },
        {
          "start_ref": "56001016",
          "start_ref_usfm": "TIT 1:16",
          "end_ref": "56001016",
          "end_ref_usfm": "TIT 1:16"
        },
        {
          "start_ref": "66018002",
          "start_ref_usfm": "REV 18:2",
          "end_ref": "66018002",
          "end_ref_usfm": "REV 18:2"
        },
        {
          "start_ref": "66017003",
          "start_ref_usfm": "REV 17:3",
          "end_ref": "66017005",
          "end_ref_usfm": "REV 17:5"
        }
      ],
      "resource": [
        {
          "reference_id": 25596,
          "content_id": 179675,
          "resource_code": "UWTranslationWords",
          "label": "शुद्ध",
          "language": "hin"
        },
        {
          "reference_id": 25674,
          "content_id": 179748,
          "resource_code": "UWTranslationWords",
          "label": "भावी कहने",
          "language": "hin"
        }
      ]
    }
  }
]