[
  {
    "content_id": 26476,
    "reference_id": 25618,
    "title": "Courage",
    "media_type": "Text",
    "index_reference": "courage",
    "language": "eng",
    "content": "<h1>courage, courageous</h1><h2>Facts:</h2><p>The term “courage” refers to boldly facing or doing something that is difficult, frightening, or dangerous.</p><ul><li><p>The term, “courageous” describes someone who shows courage, who does the right thing even when feeling afraid or pressured to give up.</p></li><li><p>A person shows courage when he faces emotional or physical pain with strength and perseverance or when he faces the threat of emotional or physical pain with emotional strength.</p></li><li><p>The expression “take courage” means “don’t be afraid” or “be assured that things will turn out well.”</p></li><li><p>When Joshua was preparing to go into the dangerous land of Canaan, Moses exhorted him to be “strong and courageous.”</p></li><li><p>The term “courageous” could also be translated as “brave” or “unafraid” or “bold.”</p></li><li><p>Depending on the context, to “have courage” could also be translated as “be emotionally strong” or “be confident” or “stand firm.”</p></li><li><p>To “speak with courage” could be translated as “speak boldly” or “speak without being afraid” or “speak confidently.”</p></li></ul><h2>Translation Suggestions</h2><p>(See also: <span data-bnType=\"resourceReference\" data-resourceId=\"25700\" data-resourceType=\"UWTranslationWords\">encourage</span>, <span data-bnType=\"resourceReference\" data-resourceId=\"UnfoldingWord_TranslatorWords_confidence\" data-resourceType=\"UWTranslationWords\">confidence</span>, <span data-bnType=\"resourceReference\" data-resourceId=\"25735\" data-resourceType=\"UWTranslationWords\">fear</span>, <span data-bnType=\"resourceReference\" data-resourceId=\"UnfoldingWord_TranslatorWords_strength\" data-resourceType=\"UWTranslationWords\">strength</span>)</p><h2>Bible References:</h2><h2>Word Data:</h2><ul><li><p>Strong’s:</p></li></ul>",
    "associations": {
      "passage": [
        {
          "start_ref": "18031034",
          "start_ref_usfm": "JOB 31:34",
          "end_ref": "18031034",
          "end_ref_usfm": "JOB 31:34"
        },
        {
          "start_ref": "18032015",
          "start_ref_usfm": "JOB 32:15",
          "end_ref": "18032015",
          "end_ref_usfm": "JOB 32:15"
        },
        {
          "start_ref": "18039022",
          "start_ref_usfm": "JOB 39:22",
          "end_ref": "18039022",
          "end_ref_usfm": "JOB 39:22"
        },
        {
          "start_ref": "20031029",
          "start_ref_usfm": "PRO 31:29",
          "end_ref": "20031029",
          "end_ref_usfm": "PRO 31:29"
        },
        {
          "start_ref": "40009002",
          "start_ref_usfm": "MAT 9:2",
          "end_ref": "40009002",
          "end_ref_usfm": "MAT 9:2"
        },
        {
          "start_ref": "40009022",
          "start_ref_usfm": "MAT 9:22",
          "end_ref": "40009022",
          "end_ref_usfm": "MAT 9:22"
        },
        {
          "start_ref": "40014027",
          "start_ref_usfm": "MAT 14:27",
          "end_ref": "40014027",
          "end_ref_usfm": "MAT 14:27"
        },
        {
          "start_ref": "41006050",
          "start_ref_usfm": "MRK 6:50",
          "end_ref": "41006050",
          "end_ref_usfm": "MRK 6:50"
        },
        {
          "start_ref": "41010049",
          "start_ref_usfm": "MRK 10:49",
          "end_ref": "41010049",
          "end_ref_usfm": "MRK 10:49"
        },
        {
          "start_ref": "43016033",
          "start_ref_usfm": "JHN 16:33",
          "end_ref": "43016033",
          "end_ref_usfm": "JHN 16:33"
        },
        {
          "start_ref": "44004036",
          "start_ref_usfm": "ACT 4:36",
          "end_ref": "44004036",
          "end_ref_usfm": "ACT 4:36"
        },
        {
          "start_ref": "44014022",
          "start_ref_usfm": "ACT 14:22",
          "end_ref": "44014022",
          "end_ref_usfm": "ACT 14:22"
        },
        {
          "start_ref": "44015031",
          "start_ref_usfm": "ACT 15:31",
          "end_ref": "44015031",
          "end_ref_usfm": "ACT 15:31"
        },
        {
          "start_ref": "44018027",
          "start_ref_usfm": "ACT 18:27",
          "end_ref": "44018027",
          "end_ref_usfm": "ACT 18:27"
        },
        {
          "start_ref": "44020001",
          "start_ref_usfm": "ACT 20:1",
          "end_ref": "44020001",
          "end_ref_usfm": "ACT 20:1"
        },
        {
          "start_ref": "44023011",
          "start_ref_usfm": "ACT 23:11",
          "end_ref": "44023011",
          "end_ref_usfm": "ACT 23:11"
        },
        {
          "start_ref": "44027022",
          "start_ref_usfm": "ACT 27:22",
          "end_ref": "44027022",
          "end_ref_usfm": "ACT 27:22"
        },
        {
          "start_ref": "44027025",
          "start_ref_usfm": "ACT 27:25",
          "end_ref": "44027025",
          "end_ref_usfm": "ACT 27:25"
        },
        {
          "start_ref": "44027036",
          "start_ref_usfm": "ACT 27:36",
          "end_ref": "44027036",
          "end_ref_usfm": "ACT 27:36"
        },
        {
          "start_ref": "44028015",
          "start_ref_usfm": "ACT 28:15",
          "end_ref": "44028015",
          "end_ref_usfm": "ACT 28:15"
        },
        {
          "start_ref": "45015004",
          "start_ref_usfm": "ROM 15:4",
          "end_ref": "45015004",
          "end_ref_usfm": "ROM 15:4"
        },
        {
          "start_ref": "45015005",
          "start_ref_usfm": "ROM 15:5",
          "end_ref": "45015005",
          "end_ref_usfm": "ROM 15:5"
        },
        {
          "start_ref": "47001006",
          "start_ref_usfm": "2CO 1:6",
          "end_ref": "47001006",
          "end_ref_usfm": "2CO 1:6"
        },
        {
          "start_ref": "47007004",
          "start_ref_usfm": "2CO 7:4",
          "end_ref": "47007004",
          "end_ref_usfm": "2CO 7:4"
        },
        {
          "start_ref": "47007006",
          "start_ref_usfm": "2CO 7:6",
          "end_ref": "47007006",
          "end_ref_usfm": "2CO 7:6"
        },
        {
          "start_ref": "49006022",
          "start_ref_usfm": "EPH 6:22",
          "end_ref": "49006022",
          "end_ref_usfm": "EPH 6:22"
        },
        {
          "start_ref": "50001014",
          "start_ref_usfm": "PHP 1:14",
          "end_ref": "50001014",
          "end_ref_usfm": "PHP 1:14"
        },
        {
          "start_ref": "50002001",
          "start_ref_usfm": "PHP 2:1",
          "end_ref": "50002001",
          "end_ref_usfm": "PHP 2:1"
        },
        {
          "start_ref": "50002019",
          "start_ref_usfm": "PHP 2:19",
          "end_ref": "50002019",
          "end_ref_usfm": "PHP 2:19"
        },
        {
          "start_ref": "51002002",
          "start_ref_usfm": "COL 2:2",
          "end_ref": "51002002",
          "end_ref_usfm": "COL 2:2"
        },
        {
          "start_ref": "51004008",
          "start_ref_usfm": "COL 4:8",
          "end_ref": "51004008",
          "end_ref_usfm": "COL 4:8"
        },
        {
          "start_ref": "56001009",
          "start_ref_usfm": "TIT 1:9",
          "end_ref": "56001009",
          "end_ref_usfm": "TIT 1:9"
        },
        {
          "start_ref": "58003013",
          "start_ref_usfm": "HEB 3:13",
          "end_ref": "58003013",
          "end_ref_usfm": "HEB 3:13"
        },
        {
          "start_ref": "58006018",
          "start_ref_usfm": "HEB 6:18",
          "end_ref": "58006018",
          "end_ref_usfm": "HEB 6:18"
        },
        {
          "start_ref": "58010025",
          "start_ref_usfm": "HEB 10:25",
          "end_ref": "58010025",
          "end_ref_usfm": "HEB 10:25"
        }
      ],
      "resource": [
        {
          "reference_id": 25700,
          "content_id": 26558,
          "resource_code": "UWTranslationWords",
          "label": "Encourage",
          "language": "eng"
        },
        {
          "reference_id": 25720,
          "content_id": 26578,
          "resource_code": "Unknown",
          "label": "Exhort",
          "language": "eng"
        },
        {
          "reference_id": 25735,
          "content_id": 26593,
          "resource_code": "UWTranslationWords",
          "label": "Fear",
          "language": "eng"
        }
      ]
    }
  }
]