[
  {
    "content_id": 26769,
    "reference_id": 25911,
    "title": "John the Apostle",
    "media_type": "Text",
    "index_reference": "john the apostle",
    "language": "eng",
    "content": "<h1>John (the apostle)</h1><h2>Facts:</h2><p>John was one of Jesus’ twelve apostles and one of Jesus’ closest friends.</p><ul><li><p>John and his brother James were sons of a fisherman named Zebedee.</p></li><li><p>In the gospel that he wrote about Jesus’ life, John referred to himself as “the disciple whom Jesus loved.” This seems to indicate that John was an especially close friend of Jesus.</p></li><li><p>The Apostle John wrote five New Testament books: the gospel of John, the Revelation of Jesus Christ, and three letters written to other believers.</p></li><li><p>Note that the Apostle John was a different person than John the Baptist.</p></li></ul><p>(Translation suggestions: How to Translate Names)</p><p>(See also: <span data-bnType=\"resourceReference\" data-resourceId=\"25466\" data-resourceType=\"UWTranslationWords\">apostle</span>, <span data-bnType=\"resourceReference\" data-resourceId=\"UnfoldingWord_TranslatorWords_reveal\" data-resourceType=\"UWTranslationWords\">reveal</span>, <span data-bnType=\"resourceReference\" data-resourceId=\"25884\" data-resourceType=\"UWTranslationWords\">James (son of Zebedee)</span>, <span data-bnType=\"resourceReference\" data-resourceId=\"25912\" data-resourceType=\"UWTranslationWords\">John (the Baptist)</span>, <span data-bnType=\"resourceReference\" data-resourceId=\"26367\" data-resourceType=\"UWTranslationWords\">Zebedee</span>)</p><h2>Bible References:</h2><ul><li><p><a href=\"https://ref.ly/Gal2:9-Gal2:10\">Galatians 2:9–10</a></p></li><li><p><a href=\"https://ref.ly/John1:19-John1:21\">John 1:19–21</a></p></li><li><p><a href=\"https://ref.ly/Mark3:17-Mark3:19\">Mark 3:17–19</a></p></li><li><p><a href=\"https://ref.ly/Matt4:21-Matt4:22\">Matthew 4:21–22</a></p></li><li><p><a href=\"https://ref.ly/Rev1:1-Rev1:3\">Revelation 1:1–3</a></p></li></ul><h2>Examples from the Bible stories:</h2><ul><li><p><strong>36:1</strong> One day, Jesus took three of his disciples, Peter, James, and <strong>John</strong> with him. (The disciple named <strong>John</strong> was not the same person who baptized Jesus.) They went up on a high mountain by themselves.</p></li><li><p><strong>44:1</strong> One day, Peter and <strong>John</strong> were going to the Temple. As they approached the Temple gate, they saw a crippled man who was begging for money.</p></li><li><p><strong>44:6</strong> The leaders of the Temple were very upset by what Peter and <strong>John</strong> were saying. So they arrested them and put them into prison.</p></li><li><p><strong>44:7</strong> The next day, the Jewish leaders brought Peter and <strong>John</strong> to the high priest and the other religious leaders. They asked Peter and <strong>John</strong>, “By what power did you heal this crippled man?”</p></li><li><p><strong>44:9</strong> The leaders were shocked that Peter and <strong>John</strong> spoke so boldly because they could see that these men were ordinary men who were uneducated. But then they remembered that these men had been with Jesus. After they threatened Peter and <strong>John</strong>, they let them go.</p></li></ul><h2>Word Data:</h2><ul><li><p>Strong’s: G24910</p></li></ul>",
    "associations": {
      "passage": [
        {
          "start_ref": "40004021",
          "start_ref_usfm": "MAT 4:21",
          "end_ref": "40004021",
          "end_ref_usfm": "MAT 4:21"
        },
        {
          "start_ref": "40010002",
          "start_ref_usfm": "MAT 10:2",
          "end_ref": "40010002",
          "end_ref_usfm": "MAT 10:2"
        },
        {
          "start_ref": "40017001",
          "start_ref_usfm": "MAT 17:1",
          "end_ref": "40017001",
          "end_ref_usfm": "MAT 17:1"
        },
        {
          "start_ref": "41001019",
          "start_ref_usfm": "MRK 1:19",
          "end_ref": "41001019",
          "end_ref_usfm": "MRK 1:19"
        },
        {
          "start_ref": "41001029",
          "start_ref_usfm": "MRK 1:29",
          "end_ref": "41001029",
          "end_ref_usfm": "MRK 1:29"
        },
        {
          "start_ref": "41003017",
          "start_ref_usfm": "MRK 3:17",
          "end_ref": "41003017",
          "end_ref_usfm": "MRK 3:17"
        },
        {
          "start_ref": "41005037",
          "start_ref_usfm": "MRK 5:37",
          "end_ref": "41005037",
          "end_ref_usfm": "MRK 5:37"
        },
        {
          "start_ref": "41009002",
          "start_ref_usfm": "MRK 9:2",
          "end_ref": "41009002",
          "end_ref_usfm": "MRK 9:2"
        },
        {
          "start_ref": "41009038",
          "start_ref_usfm": "MRK 9:38",
          "end_ref": "41009038",
          "end_ref_usfm": "MRK 9:38"
        },
        {
          "start_ref": "41010035",
          "start_ref_usfm": "MRK 10:35",
          "end_ref": "41010035",
          "end_ref_usfm": "MRK 10:35"
        },
        {
          "start_ref": "41010041",
          "start_ref_usfm": "MRK 10:41",
          "end_ref": "41010041",
          "end_ref_usfm": "MRK 10:41"
        },
        {
          "start_ref": "41013003",
          "start_ref_usfm": "MRK 13:3",
          "end_ref": "41013003",
          "end_ref_usfm": "MRK 13:3"
        },
        {
          "start_ref": "41014033",
          "start_ref_usfm": "MRK 14:33",
          "end_ref": "41014033",
          "end_ref_usfm": "MRK 14:33"
        },
        {
          "start_ref": "42005010",
          "start_ref_usfm": "LUK 5:10",
          "end_ref": "42005010",
          "end_ref_usfm": "LUK 5:10"
        },
        {
          "start_ref": "42006014",
          "start_ref_usfm": "LUK 6:14",
          "end_ref": "42006014",
          "end_ref_usfm": "LUK 6:14"
        },
        {
          "start_ref": "42008051",
          "start_ref_usfm": "LUK 8:51",
          "end_ref": "42008051",
          "end_ref_usfm": "LUK 8:51"
        },
        {
          "start_ref": "42009028",
          "start_ref_usfm": "LUK 9:28",
          "end_ref": "42009028",
          "end_ref_usfm": "LUK 9:28"
        },
        {
          "start_ref": "42009049",
          "start_ref_usfm": "LUK 9:49",
          "end_ref": "42009049",
          "end_ref_usfm": "LUK 9:49"
        },
        {
          "start_ref": "42009054",
          "start_ref_usfm": "LUK 9:54",
          "end_ref": "42009054",
          "end_ref_usfm": "LUK 9:54"
        },
        {
          "start_ref": "42022008",
          "start_ref_usfm": "LUK 22:8",
          "end_ref": "42022008",
          "end_ref_usfm": "LUK 22:8"
        },
        {
          "start_ref": "44001013",
          "start_ref_usfm": "ACT 1:13",
          "end_ref": "44001013",
          "end_ref_usfm": "ACT 1:13"
        },
        {
          "start_ref": "44003001",
          "start_ref_usfm": "ACT 3:1",
          "end_ref": "44003001",
          "end_ref_usfm": "ACT 3:1"
        },
        {
          "start_ref": "44003003",
          "start_ref_usfm": "ACT 3:3",
          "end_ref": "44003003",
          "end_ref_usfm": "ACT 3:3"
        },
        {
          "start_ref": "44003004",
          "start_ref_usfm": "ACT 3:4",
          "end_ref": "44003004",
          "end_ref_usfm": "ACT 3:4"
        },
        {
          "start_ref": "44003011",
          "start_ref_usfm": "ACT 3:11",
          "end_ref": "44003011",
          "end_ref_usfm": "ACT 3:11"
        },
        {
          "start_ref": "44004013",
          "start_ref_usfm": "ACT 4:13",
          "end_ref": "44004013",
          "end_ref_usfm": "ACT 4:13"
        },
        {
          "start_ref": "44004019",
          "start_ref_usfm": "ACT 4:19",
          "end_ref": "44004019",
          "end_ref_usfm": "ACT 4:19"
        },
        {
          "start_ref": "44008014",
          "start_ref_usfm": "ACT 8:14",
          "end_ref": "44008014",
          "end_ref_usfm": "ACT 8:14"
        },
        {
          "start_ref": "44012002",
          "start_ref_usfm": "ACT 12:2",
          "end_ref": "44012002",
          "end_ref_usfm": "ACT 12:2"
        },
        {
          "start_ref": "66001001",
          "start_ref_usfm": "REV 1:1",
          "end_ref": "66001001",
          "end_ref_usfm": "REV 1:1"
        },
        {
          "start_ref": "66001004",
          "start_ref_usfm": "REV 1:4",
          "end_ref": "66001004",
          "end_ref_usfm": "REV 1:4"
        },
        {
          "start_ref": "66001009",
          "start_ref_usfm": "REV 1:9",
          "end_ref": "66001009",
          "end_ref_usfm": "REV 1:9"
        },
        {
          "start_ref": "66022008",
          "start_ref_usfm": "REV 22:8",
          "end_ref": "66022008",
          "end_ref_usfm": "REV 22:8"
        },
        {
          "start_ref": "66001001",
          "start_ref_usfm": "REV 1:1",
          "end_ref": "66001003",
          "end_ref_usfm": "REV 1:3"
        },
        {
          "start_ref": "40004021",
          "start_ref_usfm": "MAT 4:21",
          "end_ref": "40004022",
          "end_ref_usfm": "MAT 4:22"
        },
        {
          "start_ref": "41003017",
          "start_ref_usfm": "MRK 3:17",
          "end_ref": "41003019",
          "end_ref_usfm": "MRK 3:19"
        },
        {
          "start_ref": "48002009",
          "start_ref_usfm": "GAL 2:9",
          "end_ref": "48002010",
          "end_ref_usfm": "GAL 2:10"
        },
        {
          "start_ref": "43001019",
          "start_ref_usfm": "JHN 1:19",
          "end_ref": "43001021",
          "end_ref_usfm": "JHN 1:21"
        }
      ],
      "resource": [
        {
          "reference_id": 25466,
          "content_id": 26324,
          "resource_code": "UWTranslationWords",
          "label": "Apostle",
          "language": "eng"
        },
        {
          "reference_id": 25884,
          "content_id": 26742,
          "resource_code": "UWTranslationWords",
          "label": "James Son of Zebedee",
          "language": "eng"
        },
        {
          "reference_id": 25912,
          "content_id": 26770,
          "resource_code": "UWTranslationWords",
          "label": "John the Baptist",
          "language": "eng"
        },
        {
          "reference_id": 26367,
          "content_id": 27225,
          "resource_code": "UWTranslationWords",
          "label": "Zebedee",
          "language": "eng"
        }
      ]
    }
  }
]